{"working_dir":null,"default_chunk_options":{"echo":true},"chunk_definitions":[{"row":16,"row_count":1,"visible":true,"expansion_state":0,"options":{"engine":"r","label":"setup","include":false},"document_id":"55DDB5F2","chunk_id":"csetup_chunk","chunk_label":"setup"},{"row":34,"row_count":1,"visible":true,"expansion_state":0,"options":{"engine":"r","label":"loadpacks","message":false,"results":"hide"},"document_id":"55DDB5F2","chunk_id":"cacdv95p3i599","chunk_label":"loadpacks"},{"row":99,"row_count":1,"visible":true,"expansion_state":0,"options":{"engine":"r","label":"loaddata","eval":false,"echo":true},"document_id":"55DDB5F2","chunk_id":"clyfpddpk09qg","chunk_label":"unnamed-chunk-2"},{"row":111,"row_count":1,"visible":true,"expansion_state":0,"options":{"engine":"r","label":"write","eval":false,"echo":true},"document_id":"55DDB5F2","chunk_id":"cnfjdbv9e2g9s","chunk_label":"unnamed-chunk-3"},{"row":122,"row_count":1,"visible":true,"expansion_state":0,"options":{"engine":"r","label":"rmMiss"},"document_id":"55DDB5F2","chunk_id":"cxaq3k2vdt4ka","chunk_label":"unnamed-chunk-4"},{"row":133,"row_count":1,"visible":true,"expansion_state":0,"options":{"engine":"r","label":"summaryTab"},"document_id":"55DDB5F2","chunk_id":"ce4x436t8noqb","chunk_label":"summaryTab"},{"row":153,"row_count":1,"visible":true,"expansion_state":0,"options":{"engine":"r","label":"prettyfig","fig.align":"center","fig.cap":"add a legend here"},"document_id":"55DDB5F2","chunk_id":"caupa6o5pt848","chunk_label":"unnamed-chunk-5"},{"row":163,"row_count":1,"visible":true,"expansion_state":0,"options":{"engine":"r","label":"savefig"},"document_id":"55DDB5F2","chunk_id":"cugtc4loxiwmb","chunk_label":"unnamed-chunk-6"},{"row":169,"row_count":1,"visible":true,"expansion_state":0,"options":{"engine":"r","label":"unnamed-chunk-1"},"document_id":"55DDB5F2","chunk_id":"c0ck92w6ze65j","chunk_label":"unnamed-chunk-7"},{"row":177,"row_count":1,"visible":true,"expansion_state":0,"options":{"engine":"r","label":"answer6"},"document_id":"55DDB5F2","chunk_id":"czppipl04z225","chunk_label":"unnamed-chunk-8"},{"row":189,"row_count":1,"visible":true,"expansion_state":0,"options":{"engine":"r","label":"collabFig","echo":true,"eval":true},"document_id":"55DDB5F2","chunk_id":"cuwpy0n9nusjq","chunk_label":"unnamed-chunk-9"},{"row":225,"row_count":1,"visible":true,"expansion_state":0,"options":{"engine":"r","label":"stats","echo":true,"eval":true},"document_id":"55DDB5F2","chunk_id":"chtkqggd33dug","chunk_label":"unnamed-chunk-10"},{"row":229,"row_count":1,"visible":true,"expansion_state":0,"options":{"engine":"r","label":"table1","echo":true,"eval":true,"tab.cap":"write a caption here"},"document_id":"55DDB5F2","chunk_id":"cgom0ve9up8e4","chunk_label":"unnamed-chunk-11"}],"doc_write_time":1662642943,"chunk_rendered_width":700}